LICENSE
MANIFEST.in
README.md
setup.py
py_solc_x_epvt.egg-info/PKG-INFO
py_solc_x_epvt.egg-info/SOURCES.txt
py_solc_x_epvt.egg-info/dependency_links.txt
py_solc_x_epvt.egg-info/not-zip-safe
py_solc_x_epvt.egg-info/requires.txt
py_solc_x_epvt.egg-info/top_level.txt
solcx/__init__.py
solcx/exceptions.py
solcx/install.py
solcx/main.py
solcx/wrapper.py
solcx/utils/__init__.py
solcx/utils/filesystem.py
solcx/utils/string.py
solcx/utils/types.py