Metadata-Version: 2.1
Name: py-solc-x-epvt
Version: 0.4.0
Summary: Python wrapper around the solc binary with 0.5.x support
Home-page: https://github.com/mukherjeearnab/py-solc-x
Author: Arnab Mukherjee (forked from py-solc-x by ApeWorX)
Author-email: mukherjeearnab@gmail.com
License: MIT
Keywords: ethereum solidity solc
Platform: UNKNOWN
Classifier: Intended Audience :: Developers
Classifier: License :: OSI Approved :: MIT License
Classifier: Natural Language :: English
Classifier: Programming Language :: Python :: 3
Classifier: Programming Language :: Python :: 3.4
Classifier: Programming Language :: Python :: 3.5
Classifier: Programming Language :: Python :: 3.6
Classifier: Programming Language :: Python :: 3.7
Requires-Python: >=3.4, <4
License-File: LICENSE
